iog/__init__.py
iog/cli.py
iog_sdk-0.0.1.dist-info/AUTHORS.rst
iog_sdk-0.0.1.dist-info/LICENSE
iog_sdk-0.0.1.dist-info/METADATA
iog_sdk-0.0.1.dist-info/WHEEL
iog_sdk-0.0.1.dist-info/entry_points.txt
iog_sdk-0.0.1.dist-info/top_level.txt
iog_sdk-0.0.1.dist-info/RECORD
